{
  "url": "https://mita.law/our-team/d-sinclaire-owen-welch",
  "viewport": {
    "name": "mobile",
    "width": 390,
    "height": 844
  },
  "mode": 1,
  "options": {
    "delayMs": 100,
    "scrollDelayMs": 0,
    "waitForSelector": null,
    "waitTimeoutMs": 20000,
    "fastStabilizeMs": 4000,
    "stableIterations": 6,
    "maxPendingImages": 5,
    "sweepEnabled": true,
    "sweepSteps": 6,
    "sweepWaitMs": 250,
    "spotsEnabled": true,
    "spotPcts": [
      40,
      80
    ],
    "noFullPage": false,
    "blockNoise": true,
    "sitemap": null,
    "include": null,
    "exclude": null,
    "limit": 0,
    "sameHostOnly": false
  },
  "stability": {
    "ok": true,
    "height": 3357,
    "pendingImgs": 0,
    "domSize": 478
  },
  "ts": "2025-12-31T22:12:53.169Z"
}